nekoslife/__functions.py
nekoslife/__init__.py
nekoslife-0.0.1.dist-info/LICENSE
nekoslife-0.0.1.dist-info/METADATA
nekoslife-0.0.1.dist-info/WHEEL
nekoslife-0.0.1.dist-info/top_level.txt
nekoslife-0.0.1.dist-info/RECORD
