Metadata-Version: 2.1
Name: nekoslife
Version: 0.0.1
Summary: An unofficial wrapper for nekos.life api with proxy support.
Home-page: https://github.com/Blank-c/NekosLife
Author: Blank-c
Keywords: nekoslife
License-File: LICENSE
Requires-Dist: aiohttp
